{
	"ColaAVL" : 0,
	"ColaBinario" : 0,
	"ColaEspanta" : 0,
	"ColaHEAP" : 0,
	"ColaSplay" : 4,
	"Dinero" : 95999.0,
	"EspantapajarosDispo" : 0,
	"FrutosAVL" : 0,
	"FrutosBinario" : 0,
	"FrutosHeap" : 0,
	"FrutosSplay" : 44,
	"Matriz" : 
	[
		[
			null,
			null,
			null,
			null,
			null,
			null,
			null,
			null,
			null,
			null
		],
		[
			null,
			null,
			null,
			null,
			null,
			null,
			null,
			null,
			null,
			null
		],
		[
			null,
			null,
			null,
			null,
			null,
			null,
			null,
			null,
			null,
			null
		],
		[
			null,
			null,
			null,
			null,
			null,
			null,
			null,
			null,
			null,
			null
		],
		[
			null,
			null,
			null,
			null,
			null,
			null,
			null,
			null,
			null,
			null
		],
		[
			null,
			null,
			{
				"ejecutando" : false,
				"letra" : "E"
			},
			{
				"ejecutando" : false,
				"letra" : "g"
			},
			null,
			null,
			null,
			{
				"ejecutando" : false,
				"letra" : "E"
			},
			null,
			null
		],
		[
			null,
			null,
			null,
			null,
			null,
			null,
			{
				"ejecutando" : false,
				"letra" : "g"
			},
			null,
			null,
			null
		],
		[
			null,
			null,
			null,
			null,
			null,
			null,
			null,
			null,
			null,
			null
		],
		[
			null,
			null,
			null,
			null,
			null,
			null,
			null,
			null,
			null,
			null
		],
		[
			null,
			null,
			null,
			null,
			null,
			null,
			null,
			null,
			null,
			null
		]
	],
	"NombrePartida" : "partidaaguacate.json",
	"PrecioAVL" : 349.8699951171875,
	"PrecioBinario" : 99.8699951171875,
	"PrecioEspanta" : 199.87001037597656,
	"PrecioHeap" : 129.87001037597656,
	"PrecioSplay" : 599.8499755859375,
	"SettingAparicionCuervos" : 0,
	"SettingAparicionOveja" : 0,
	"SettingAparicionPlagas" : 0,
	"SettingPorcentCuervos" : 0,
	"SettingPorcentOveja" : 0,
	"SettingPorcentPlagas" : 0,
	"SettingTiempoCuervos" : 0,
	"SettingTiempoFrutosCuervos" : 0,
	"SettingTiempoFrutosOveja" : 0,
	"SettingTiempoOveja" : 0,
	"SettingTiempoPlagas" : 0,
	"SettingfrutosCuervos" : 0,
	"SettingfrutosOveja" : 0,
	"SettingsMercadoAparicion" : 0,
	"SettingsMercadoApertura" : 0
}
